{
  "store": "vre00g-8b.myshopify.com",
  "generatedAt": "2026-04-26T22:07:08.840Z",
  "productCount": 10,
  "variantCount": 59,
  "missingHandles": [],
  "rows": [
    {
      "Product Handle": "clara-waffle-cotton-throw",
      "Product Title": "Clara Waffle Cotton Throw",
      "Product Status": "ACTIVE",
      "Shopify Product ID": "15796866023758",
      "Shopify Product GID": "gid://shopify/Product/15796866023758",
      "Shopify Admin URL": "https://admin.shopify.com/store/vre00g-8b/products/15796866023758",
      "CJ Source SKU": "CJYD205705801AZ",
      "CJ Product URL": "https://cjdropshipping.com/product/cotton-waffle-knit-chenille-towel-sofa-cover-blanket-p-2406100547151615200.html",
      "Variant Title": "Khaki / 100 x 150 cm",
      "Variant SKU": "CM-CJYD205705801AZ-KHAKI-100-X-150-CM",
      "Shopify Variant ID": "59516335554894",
      "Shopify Variant GID": "gid://shopify/ProductVariant/59516335554894",
      "Inventory Item ID": "57931503075662",
      "Inventory Item GID": "gid://shopify/InventoryItem/57931503075662",
      "Inventory Tracked": "FALSE",
      "Inventory Policy": "CONTINUE",
      "Option 1 Name": "Color",
      "Option 1 Value": "Khaki",
      "Option 2 Name": "Size",
      "Option 2 Value": "100 x 150 cm",
      "Option 3 Name": "",
      "Option 3 Value": "",
      "CJ Connection Step": "CJ > Products > Store Products > Unconnected > Connect/Add Automatic Connection",
      "Connection Status": "needs-cj-connection"
    },
    {
      "Product Handle": "clara-waffle-cotton-throw",
      "Product Title": "Clara Waffle Cotton Throw",
      "Product Status": "ACTIVE",
      "Shopify Product ID": "15796866023758",
      "Shopify Product GID": "gid://shopify/Product/15796866023758",
      "Shopify Admin URL": "https://admin.shopify.com/store/vre00g-8b/products/15796866023758",
      "CJ Source SKU": "CJYD205705801AZ",
      "CJ Product URL": "https://cjdropshipping.com/product/cotton-waffle-knit-chenille-towel-sofa-cover-blanket-p-2406100547151615200.html",
      "Variant Title": "Khaki / 150 x 200 cm",
      "Variant SKU": "CM-CJYD205705801AZ-KHAKI-150-X-200-CM",
      "Shopify Variant ID": "59516335587662",
      "Shopify Variant GID": "gid://shopify/ProductVariant/59516335587662",
      "Inventory Item ID": "57931503108430",
      "Inventory Item GID": "gid://shopify/InventoryItem/57931503108430",
      "Inventory Tracked": "FALSE",
      "Inventory Policy": "CONTINUE",
      "Option 1 Name": "Color",
      "Option 1 Value": "Khaki",
      "Option 2 Name": "Size",
      "Option 2 Value": "150 x 200 cm",
      "Option 3 Name": "",
      "Option 3 Value": "",
      "CJ Connection Step": "CJ > Products > Store Products > Unconnected > Connect/Add Automatic Connection",
      "Connection Status": "needs-cj-connection"
    },
    {
      "Product Handle": "clara-waffle-cotton-throw",
      "Product Title": "Clara Waffle Cotton Throw",
      "Product Status": "ACTIVE",
      "Shopify Product ID": "15796866023758",
      "Shopify Product GID": "gid://shopify/Product/15796866023758",
      "Shopify Admin URL": "https://admin.shopify.com/store/vre00g-8b/products/15796866023758",
      "CJ Source SKU": "CJYD205705801AZ",
      "CJ Product URL": "https://cjdropshipping.com/product/cotton-waffle-knit-chenille-towel-sofa-cover-blanket-p-2406100547151615200.html",
      "Variant Title": "Khaki / 200 x 230 cm",
      "Variant SKU": "CM-CJYD205705801AZ-KHAKI-200-X-230-CM",
      "Shopify Variant ID": "59516335620430",
      "Shopify Variant GID": "gid://shopify/ProductVariant/59516335620430",
      "Inventory Item ID": "57931503141198",
      "Inventory Item GID": "gid://shopify/InventoryItem/57931503141198",
      "Inventory Tracked": "FALSE",
      "Inventory Policy": "CONTINUE",
      "Option 1 Name": "Color",
      "Option 1 Value": "Khaki",
      "Option 2 Name": "Size",
      "Option 2 Value": "200 x 230 cm",
      "Option 3 Name": "",
      "Option 3 Value": "",
      "CJ Connection Step": "CJ > Products > Store Products > Unconnected > Connect/Add Automatic Connection",
      "Connection Status": "needs-cj-connection"
    },
    {
      "Product Handle": "clara-waffle-cotton-throw",
      "Product Title": "Clara Waffle Cotton Throw",
      "Product Status": "ACTIVE",
      "Shopify Product ID": "15796866023758",
      "Shopify Product GID": "gid://shopify/Product/15796866023758",
      "Shopify Admin URL": "https://admin.shopify.com/store/vre00g-8b/products/15796866023758",
      "CJ Source SKU": "CJYD205705801AZ",
      "CJ Product URL": "https://cjdropshipping.com/product/cotton-waffle-knit-chenille-towel-sofa-cover-blanket-p-2406100547151615200.html",
      "Variant Title": "Silver Gray / 100 x 150 cm",
      "Variant SKU": "CM-CJYD205705801AZ-SILVER-GRAY-100-X-150-CM",
      "Shopify Variant ID": "59516335653198",
      "Shopify Variant GID": "gid://shopify/ProductVariant/59516335653198",
      "Inventory Item ID": "57931503173966",
      "Inventory Item GID": "gid://shopify/InventoryItem/57931503173966",
      "Inventory Tracked": "FALSE",
      "Inventory Policy": "CONTINUE",
      "Option 1 Name": "Color",
      "Option 1 Value": "Silver Gray",
      "Option 2 Name": "Size",
      "Option 2 Value": "100 x 150 cm",
      "Option 3 Name": "",
      "Option 3 Value": "",
      "CJ Connection Step": "CJ > Products > Store Products > Unconnected > Connect/Add Automatic Connection",
      "Connection Status": "needs-cj-connection"
    },
    {
      "Product Handle": "clara-waffle-cotton-throw",
      "Product Title": "Clara Waffle Cotton Throw",
      "Product Status": "ACTIVE",
      "Shopify Product ID": "15796866023758",
      "Shopify Product GID": "gid://shopify/Product/15796866023758",
      "Shopify Admin URL": "https://admin.shopify.com/store/vre00g-8b/products/15796866023758",
      "CJ Source SKU": "CJYD205705801AZ",
      "CJ Product URL": "https://cjdropshipping.com/product/cotton-waffle-knit-chenille-towel-sofa-cover-blanket-p-2406100547151615200.html",
      "Variant Title": "Silver Gray / 150 x 200 cm",
      "Variant SKU": "CM-CJYD205705801AZ-SILVER-GRAY-150-X-200-CM",
      "Shopify Variant ID": "59516335685966",
      "Shopify Variant GID": "gid://shopify/ProductVariant/59516335685966",
      "Inventory Item ID": "57931503206734",
      "Inventory Item GID": "gid://shopify/InventoryItem/57931503206734",
      "Inventory Tracked": "FALSE",
      "Inventory Policy": "CONTINUE",
      "Option 1 Name": "Color",
      "Option 1 Value": "Silver Gray",
      "Option 2 Name": "Size",
      "Option 2 Value": "150 x 200 cm",
      "Option 3 Name": "",
      "Option 3 Value": "",
      "CJ Connection Step": "CJ > Products > Store Products > Unconnected > Connect/Add Automatic Connection",
      "Connection Status": "needs-cj-connection"
    },
    {
      "Product Handle": "clara-waffle-cotton-throw",
      "Product Title": "Clara Waffle Cotton Throw",
      "Product Status": "ACTIVE",
      "Shopify Product ID": "15796866023758",
      "Shopify Product GID": "gid://shopify/Product/15796866023758",
      "Shopify Admin URL": "https://admin.shopify.com/store/vre00g-8b/products/15796866023758",
      "CJ Source SKU": "CJYD205705801AZ",
      "CJ Product URL": "https://cjdropshipping.com/product/cotton-waffle-knit-chenille-towel-sofa-cover-blanket-p-2406100547151615200.html",
      "Variant Title": "Silver Gray / 200 x 230 cm",
      "Variant SKU": "CM-CJYD205705801AZ-SILVER-GRAY-200-X-230-CM",
      "Shopify Variant ID": "59516335718734",
      "Shopify Variant GID": "gid://shopify/ProductVariant/59516335718734",
      "Inventory Item ID": "57931503239502",
      "Inventory Item GID": "gid://shopify/InventoryItem/57931503239502",
      "Inventory Tracked": "FALSE",
      "Inventory Policy": "CONTINUE",
      "Option 1 Name": "Color",
      "Option 1 Value": "Silver Gray",
      "Option 2 Name": "Size",
      "Option 2 Value": "200 x 230 cm",
      "Option 3 Name": "",
      "Option 3 Value": "",
      "CJ Connection Step": "CJ > Products > Store Products > Unconnected > Connect/Add Automatic Connection",
      "Connection Status": "needs-cj-connection"
    },
    {
      "Product Handle": "clara-waffle-cotton-throw",
      "Product Title": "Clara Waffle Cotton Throw",
      "Product Status": "ACTIVE",
      "Shopify Product ID": "15796866023758",
      "Shopify Product GID": "gid://shopify/Product/15796866023758",
      "Shopify Admin URL": "https://admin.shopify.com/store/vre00g-8b/products/15796866023758",
      "CJ Source SKU": "CJYD205705801AZ",
      "CJ Product URL": "https://cjdropshipping.com/product/cotton-waffle-knit-chenille-towel-sofa-cover-blanket-p-2406100547151615200.html",
      "Variant Title": "Green / 100 x 150 cm",
      "Variant SKU": "CM-CJYD205705801AZ-GREEN-100-X-150-CM",
      "Shopify Variant ID": "59516335751502",
      "Shopify Variant GID": "gid://shopify/ProductVariant/59516335751502",
      "Inventory Item ID": "57931503272270",
      "Inventory Item GID": "gid://shopify/InventoryItem/57931503272270",
      "Inventory Tracked": "FALSE",
      "Inventory Policy": "CONTINUE",
      "Option 1 Name": "Color",
      "Option 1 Value": "Green",
      "Option 2 Name": "Size",
      "Option 2 Value": "100 x 150 cm",
      "Option 3 Name": "",
      "Option 3 Value": "",
      "CJ Connection Step": "CJ > Products > Store Products > Unconnected > Connect/Add Automatic Connection",
      "Connection Status": "needs-cj-connection"
    },
    {
      "Product Handle": "clara-waffle-cotton-throw",
      "Product Title": "Clara Waffle Cotton Throw",
      "Product Status": "ACTIVE",
      "Shopify Product ID": "15796866023758",
      "Shopify Product GID": "gid://shopify/Product/15796866023758",
      "Shopify Admin URL": "https://admin.shopify.com/store/vre00g-8b/products/15796866023758",
      "CJ Source SKU": "CJYD205705801AZ",
      "CJ Product URL": "https://cjdropshipping.com/product/cotton-waffle-knit-chenille-towel-sofa-cover-blanket-p-2406100547151615200.html",
      "Variant Title": "Green / 150 x 200 cm",
      "Variant SKU": "CM-CJYD205705801AZ-GREEN-150-X-200-CM",
      "Shopify Variant ID": "59516335784270",
      "Shopify Variant GID": "gid://shopify/ProductVariant/59516335784270",
      "Inventory Item ID": "57931503305038",
      "Inventory Item GID": "gid://shopify/InventoryItem/57931503305038",
      "Inventory Tracked": "FALSE",
      "Inventory Policy": "CONTINUE",
      "Option 1 Name": "Color",
      "Option 1 Value": "Green",
      "Option 2 Name": "Size",
      "Option 2 Value": "150 x 200 cm",
      "Option 3 Name": "",
      "Option 3 Value": "",
      "CJ Connection Step": "CJ > Products > Store Products > Unconnected > Connect/Add Automatic Connection",
      "Connection Status": "needs-cj-connection"
    },
    {
      "Product Handle": "clara-waffle-cotton-throw",
      "Product Title": "Clara Waffle Cotton Throw",
      "Product Status": "ACTIVE",
      "Shopify Product ID": "15796866023758",
      "Shopify Product GID": "gid://shopify/Product/15796866023758",
      "Shopify Admin URL": "https://admin.shopify.com/store/vre00g-8b/products/15796866023758",
      "CJ Source SKU": "CJYD205705801AZ",
      "CJ Product URL": "https://cjdropshipping.com/product/cotton-waffle-knit-chenille-towel-sofa-cover-blanket-p-2406100547151615200.html",
      "Variant Title": "Green / 200 x 230 cm",
      "Variant SKU": "CM-CJYD205705801AZ-GREEN-200-X-230-CM",
      "Shopify Variant ID": "59516335817038",
      "Shopify Variant GID": "gid://shopify/ProductVariant/59516335817038",
      "Inventory Item ID": "57931503337806",
      "Inventory Item GID": "gid://shopify/InventoryItem/57931503337806",
      "Inventory Tracked": "FALSE",
      "Inventory Policy": "CONTINUE",
      "Option 1 Name": "Color",
      "Option 1 Value": "Green",
      "Option 2 Name": "Size",
      "Option 2 Value": "200 x 230 cm",
      "Option 3 Name": "",
      "Option 3 Value": "",
      "CJ Connection Step": "CJ > Products > Store Products > Unconnected > Connect/Add Automatic Connection",
      "Connection Status": "needs-cj-connection"
    },
    {
      "Product Handle": "luma-tassel-cotton-throw",
      "Product Title": "Luma Tassel Cotton Throw",
      "Product Status": "ACTIVE",
      "Shopify Product ID": "15796866449742",
      "Shopify Product GID": "gid://shopify/Product/15796866449742",
      "Shopify Admin URL": "https://admin.shopify.com/store/vre00g-8b/products/15796866449742",
      "CJ Source SKU": "CJYD205807501AZ",
      "CJ Product URL": "https://cjdropshipping.com/product/household-fashion-tassel-simple-cloth-blanket-p-2406110909121605500.html",
      "Variant Title": "Curry / 80 x 130 cm",
      "Variant SKU": "CM-CJYD205807501AZ-CURRY-80-X-130-CM",
      "Shopify Variant ID": "59516337815886",
      "Shopify Variant GID": "gid://shopify/ProductVariant/59516337815886",
      "Inventory Item ID": "57931505336654",
      "Inventory Item GID": "gid://shopify/InventoryItem/57931505336654",
      "Inventory Tracked": "FALSE",
      "Inventory Policy": "CONTINUE",
      "Option 1 Name": "Color",
      "Option 1 Value": "Curry",
      "Option 2 Name": "Size",
      "Option 2 Value": "80 x 130 cm",
      "Option 3 Name": "",
      "Option 3 Value": "",
      "CJ Connection Step": "CJ > Products > Store Products > Unconnected > Connect/Add Automatic Connection",
      "Connection Status": "needs-cj-connection"
    },
    {
      "Product Handle": "luma-tassel-cotton-throw",
      "Product Title": "Luma Tassel Cotton Throw",
      "Product Status": "ACTIVE",
      "Shopify Product ID": "15796866449742",
      "Shopify Product GID": "gid://shopify/Product/15796866449742",
      "Shopify Admin URL": "https://admin.shopify.com/store/vre00g-8b/products/15796866449742",
      "CJ Source SKU": "CJYD205807501AZ",
      "CJ Product URL": "https://cjdropshipping.com/product/household-fashion-tassel-simple-cloth-blanket-p-2406110909121605500.html",
      "Variant Title": "Curry / 130 x 170 cm",
      "Variant SKU": "CM-CJYD205807501AZ-CURRY-130-X-170-CM",
      "Shopify Variant ID": "59516337848654",
      "Shopify Variant GID": "gid://shopify/ProductVariant/59516337848654",
      "Inventory Item ID": "57931505369422",
      "Inventory Item GID": "gid://shopify/InventoryItem/57931505369422",
      "Inventory Tracked": "FALSE",
      "Inventory Policy": "CONTINUE",
      "Option 1 Name": "Color",
      "Option 1 Value": "Curry",
      "Option 2 Name": "Size",
      "Option 2 Value": "130 x 170 cm",
      "Option 3 Name": "",
      "Option 3 Value": "",
      "CJ Connection Step": "CJ > Products > Store Products > Unconnected > Connect/Add Automatic Connection",
      "Connection Status": "needs-cj-connection"
    },
    {
      "Product Handle": "luma-tassel-cotton-throw",
      "Product Title": "Luma Tassel Cotton Throw",
      "Product Status": "ACTIVE",
      "Shopify Product ID": "15796866449742",
      "Shopify Product GID": "gid://shopify/Product/15796866449742",
      "Shopify Admin URL": "https://admin.shopify.com/store/vre00g-8b/products/15796866449742",
      "CJ Source SKU": "CJYD205807501AZ",
      "CJ Product URL": "https://cjdropshipping.com/product/household-fashion-tassel-simple-cloth-blanket-p-2406110909121605500.html",
      "Variant Title": "Curry / 150 x 200 cm",
      "Variant SKU": "CM-CJYD205807501AZ-CURRY-150-X-200-CM",
      "Shopify Variant ID": "59516337881422",
      "Shopify Variant GID": "gid://shopify/ProductVariant/59516337881422",
      "Inventory Item ID": "57931505402190",
      "Inventory Item GID": "gid://shopify/InventoryItem/57931505402190",
      "Inventory Tracked": "FALSE",
      "Inventory Policy": "CONTINUE",
      "Option 1 Name": "Color",
      "Option 1 Value": "Curry",
      "Option 2 Name": "Size",
      "Option 2 Value": "150 x 200 cm",
      "Option 3 Name": "",
      "Option 3 Value": "",
      "CJ Connection Step": "CJ > Products > Store Products > Unconnected > Connect/Add Automatic Connection",
      "Connection Status": "needs-cj-connection"
    },
    {
      "Product Handle": "luma-tassel-cotton-throw",
      "Product Title": "Luma Tassel Cotton Throw",
      "Product Status": "ACTIVE",
      "Shopify Product ID": "15796866449742",
      "Shopify Product GID": "gid://shopify/Product/15796866449742",
      "Shopify Admin URL": "https://admin.shopify.com/store/vre00g-8b/products/15796866449742",
      "CJ Source SKU": "CJYD205807501AZ",
      "CJ Product URL": "https://cjdropshipping.com/product/household-fashion-tassel-simple-cloth-blanket-p-2406110909121605500.html",
      "Variant Title": "Beige / 80 x 130 cm",
      "Variant SKU": "CM-CJYD205807501AZ-BEIGE-80-X-130-CM",
      "Shopify Variant ID": "59516337914190",
      "Shopify Variant GID": "gid://shopify/ProductVariant/59516337914190",
      "Inventory Item ID": "57931505434958",
      "Inventory Item GID": "gid://shopify/InventoryItem/57931505434958",
      "Inventory Tracked": "FALSE",
      "Inventory Policy": "CONTINUE",
      "Option 1 Name": "Color",
      "Option 1 Value": "Beige",
      "Option 2 Name": "Size",
      "Option 2 Value": "80 x 130 cm",
      "Option 3 Name": "",
      "Option 3 Value": "",
      "CJ Connection Step": "CJ > Products > Store Products > Unconnected > Connect/Add Automatic Connection",
      "Connection Status": "needs-cj-connection"
    },
    {
      "Product Handle": "luma-tassel-cotton-throw",
      "Product Title": "Luma Tassel Cotton Throw",
      "Product Status": "ACTIVE",
      "Shopify Product ID": "15796866449742",
      "Shopify Product GID": "gid://shopify/Product/15796866449742",
      "Shopify Admin URL": "https://admin.shopify.com/store/vre00g-8b/products/15796866449742",
      "CJ Source SKU": "CJYD205807501AZ",
      "CJ Product URL": "https://cjdropshipping.com/product/household-fashion-tassel-simple-cloth-blanket-p-2406110909121605500.html",
      "Variant Title": "Beige / 130 x 170 cm",
      "Variant SKU": "CM-CJYD205807501AZ-BEIGE-130-X-170-CM",
      "Shopify Variant ID": "59516337946958",
      "Shopify Variant GID": "gid://shopify/ProductVariant/59516337946958",
      "Inventory Item ID": "57931505467726",
      "Inventory Item GID": "gid://shopify/InventoryItem/57931505467726",
      "Inventory Tracked": "FALSE",
      "Inventory Policy": "CONTINUE",
      "Option 1 Name": "Color",
      "Option 1 Value": "Beige",
      "Option 2 Name": "Size",
      "Option 2 Value": "130 x 170 cm",
      "Option 3 Name": "",
      "Option 3 Value": "",
      "CJ Connection Step": "CJ > Products > Store Products > Unconnected > Connect/Add Automatic Connection",
      "Connection Status": "needs-cj-connection"
    },
    {
      "Product Handle": "luma-tassel-cotton-throw",
      "Product Title": "Luma Tassel Cotton Throw",
      "Product Status": "ACTIVE",
      "Shopify Product ID": "15796866449742",
      "Shopify Product GID": "gid://shopify/Product/15796866449742",
      "Shopify Admin URL": "https://admin.shopify.com/store/vre00g-8b/products/15796866449742",
      "CJ Source SKU": "CJYD205807501AZ",
      "CJ Product URL": "https://cjdropshipping.com/product/household-fashion-tassel-simple-cloth-blanket-p-2406110909121605500.html",
      "Variant Title": "Beige / 150 x 200 cm",
      "Variant SKU": "CM-CJYD205807501AZ-BEIGE-150-X-200-CM",
      "Shopify Variant ID": "59516337979726",
      "Shopify Variant GID": "gid://shopify/ProductVariant/59516337979726",
      "Inventory Item ID": "57931505500494",
      "Inventory Item GID": "gid://shopify/InventoryItem/57931505500494",
      "Inventory Tracked": "FALSE",
      "Inventory Policy": "CONTINUE",
      "Option 1 Name": "Color",
      "Option 1 Value": "Beige",
      "Option 2 Name": "Size",
      "Option 2 Value": "150 x 200 cm",
      "Option 3 Name": "",
      "Option 3 Value": "",
      "CJ Connection Step": "CJ > Products > Store Products > Unconnected > Connect/Add Automatic Connection",
      "Connection Status": "needs-cj-connection"
    },
    {
      "Product Handle": "luma-tassel-cotton-throw",
      "Product Title": "Luma Tassel Cotton Throw",
      "Product Status": "ACTIVE",
      "Shopify Product ID": "15796866449742",
      "Shopify Product GID": "gid://shopify/Product/15796866449742",
      "Shopify Admin URL": "https://admin.shopify.com/store/vre00g-8b/products/15796866449742",
      "CJ Source SKU": "CJYD205807501AZ",
      "CJ Product URL": "https://cjdropshipping.com/product/household-fashion-tassel-simple-cloth-blanket-p-2406110909121605500.html",
      "Variant Title": "Gray / 80 x 130 cm",
      "Variant SKU": "CM-CJYD205807501AZ-GRAY-80-X-130-CM",
      "Shopify Variant ID": "59516338012494",
      "Shopify Variant GID": "gid://shopify/ProductVariant/59516338012494",
      "Inventory Item ID": "57931505533262",
      "Inventory Item GID": "gid://shopify/InventoryItem/57931505533262",
      "Inventory Tracked": "FALSE",
      "Inventory Policy": "CONTINUE",
      "Option 1 Name": "Color",
      "Option 1 Value": "Gray",
      "Option 2 Name": "Size",
      "Option 2 Value": "80 x 130 cm",
      "Option 3 Name": "",
      "Option 3 Value": "",
      "CJ Connection Step": "CJ > Products > Store Products > Unconnected > Connect/Add Automatic Connection",
      "Connection Status": "needs-cj-connection"
    },
    {
      "Product Handle": "luma-tassel-cotton-throw",
      "Product Title": "Luma Tassel Cotton Throw",
      "Product Status": "ACTIVE",
      "Shopify Product ID": "15796866449742",
      "Shopify Product GID": "gid://shopify/Product/15796866449742",
      "Shopify Admin URL": "https://admin.shopify.com/store/vre00g-8b/products/15796866449742",
      "CJ Source SKU": "CJYD205807501AZ",
      "CJ Product URL": "https://cjdropshipping.com/product/household-fashion-tassel-simple-cloth-blanket-p-2406110909121605500.html",
      "Variant Title": "Gray / 130 x 170 cm",
      "Variant SKU": "CM-CJYD205807501AZ-GRAY-130-X-170-CM",
      "Shopify Variant ID": "59516338045262",
      "Shopify Variant GID": "gid://shopify/ProductVariant/59516338045262",
      "Inventory Item ID": "57931505566030",
      "Inventory Item GID": "gid://shopify/InventoryItem/57931505566030",
      "Inventory Tracked": "FALSE",
      "Inventory Policy": "CONTINUE",
      "Option 1 Name": "Color",
      "Option 1 Value": "Gray",
      "Option 2 Name": "Size",
      "Option 2 Value": "130 x 170 cm",
      "Option 3 Name": "",
      "Option 3 Value": "",
      "CJ Connection Step": "CJ > Products > Store Products > Unconnected > Connect/Add Automatic Connection",
      "Connection Status": "needs-cj-connection"
    },
    {
      "Product Handle": "luma-tassel-cotton-throw",
      "Product Title": "Luma Tassel Cotton Throw",
      "Product Status": "ACTIVE",
      "Shopify Product ID": "15796866449742",
      "Shopify Product GID": "gid://shopify/Product/15796866449742",
      "Shopify Admin URL": "https://admin.shopify.com/store/vre00g-8b/products/15796866449742",
      "CJ Source SKU": "CJYD205807501AZ",
      "CJ Product URL": "https://cjdropshipping.com/product/household-fashion-tassel-simple-cloth-blanket-p-2406110909121605500.html",
      "Variant Title": "Gray / 150 x 200 cm",
      "Variant SKU": "CM-CJYD205807501AZ-GRAY-150-X-200-CM",
      "Shopify Variant ID": "59516338078030",
      "Shopify Variant GID": "gid://shopify/ProductVariant/59516338078030",
      "Inventory Item ID": "57931505598798",
      "Inventory Item GID": "gid://shopify/InventoryItem/57931505598798",
      "Inventory Tracked": "FALSE",
      "Inventory Policy": "CONTINUE",
      "Option 1 Name": "Color",
      "Option 1 Value": "Gray",
      "Option 2 Name": "Size",
      "Option 2 Value": "150 x 200 cm",
      "Option 3 Name": "",
      "Option 3 Value": "",
      "CJ Connection Step": "CJ > Products > Store Products > Unconnected > Connect/Add Automatic Connection",
      "Connection Status": "needs-cj-connection"
    },
    {
      "Product Handle": "sera-woven-table-runner",
      "Product Title": "Sera Woven Table Runner",
      "Product Status": "ACTIVE",
      "Shopify Product ID": "15796866548046",
      "Shopify Product GID": "gid://shopify/Product/15796866548046",
      "Shopify Admin URL": "https://admin.shopify.com/store/vre00g-8b/products/15796866548046",
      "CJ Source SKU": "CJYD239088001AZ",
      "CJ Product URL": "https://cjdropshipping.com/product/home-decoration-simple-woven-cotton-and-linen-table-runner-p-2506020359111604900.html",
      "Variant Title": "Waffle / 33 x 160 cm",
      "Variant SKU": "CM-CJYD239088001AZ-WAFFLE-33-X-160-CM",
      "Shopify Variant ID": "59516338405710",
      "Shopify Variant GID": "gid://shopify/ProductVariant/59516338405710",
      "Inventory Item ID": "57931505926478",
      "Inventory Item GID": "gid://shopify/InventoryItem/57931505926478",
      "Inventory Tracked": "FALSE",
      "Inventory Policy": "CONTINUE",
      "Option 1 Name": "Pattern",
      "Option 1 Value": "Waffle",
      "Option 2 Name": "Size",
      "Option 2 Value": "33 x 160 cm",
      "Option 3 Name": "",
      "Option 3 Value": "",
      "CJ Connection Step": "CJ > Products > Store Products > Unconnected > Connect/Add Automatic Connection",
      "Connection Status": "needs-cj-connection"
    },
    {
      "Product Handle": "sera-woven-table-runner",
      "Product Title": "Sera Woven Table Runner",
      "Product Status": "ACTIVE",
      "Shopify Product ID": "15796866548046",
      "Shopify Product GID": "gid://shopify/Product/15796866548046",
      "Shopify Admin URL": "https://admin.shopify.com/store/vre00g-8b/products/15796866548046",
      "CJ Source SKU": "CJYD239088001AZ",
      "CJ Product URL": "https://cjdropshipping.com/product/home-decoration-simple-woven-cotton-and-linen-table-runner-p-2506020359111604900.html",
      "Variant Title": "Waffle / 33 x 183 cm",
      "Variant SKU": "CM-CJYD239088001AZ-WAFFLE-33-X-183-CM",
      "Shopify Variant ID": "59516338438478",
      "Shopify Variant GID": "gid://shopify/ProductVariant/59516338438478",
      "Inventory Item ID": "57931505959246",
      "Inventory Item GID": "gid://shopify/InventoryItem/57931505959246",
      "Inventory Tracked": "FALSE",
      "Inventory Policy": "CONTINUE",
      "Option 1 Name": "Pattern",
      "Option 1 Value": "Waffle",
      "Option 2 Name": "Size",
      "Option 2 Value": "33 x 183 cm",
      "Option 3 Name": "",
      "Option 3 Value": "",
      "CJ Connection Step": "CJ > Products > Store Products > Unconnected > Connect/Add Automatic Connection",
      "Connection Status": "needs-cj-connection"
    },
    {
      "Product Handle": "sera-woven-table-runner",
      "Product Title": "Sera Woven Table Runner",
      "Product Status": "ACTIVE",
      "Shopify Product ID": "15796866548046",
      "Shopify Product GID": "gid://shopify/Product/15796866548046",
      "Shopify Admin URL": "https://admin.shopify.com/store/vre00g-8b/products/15796866548046",
      "CJ Source SKU": "CJYD239088001AZ",
      "CJ Product URL": "https://cjdropshipping.com/product/home-decoration-simple-woven-cotton-and-linen-table-runner-p-2506020359111604900.html",
      "Variant Title": "Waffle / 33 x 200 cm",
      "Variant SKU": "CM-CJYD239088001AZ-WAFFLE-33-X-200-CM",
      "Shopify Variant ID": "59516338471246",
      "Shopify Variant GID": "gid://shopify/ProductVariant/59516338471246",
      "Inventory Item ID": "57931505992014",
      "Inventory Item GID": "gid://shopify/InventoryItem/57931505992014",
      "Inventory Tracked": "FALSE",
      "Inventory Policy": "CONTINUE",
      "Option 1 Name": "Pattern",
      "Option 1 Value": "Waffle",
      "Option 2 Name": "Size",
      "Option 2 Value": "33 x 200 cm",
      "Option 3 Name": "",
      "Option 3 Value": "",
      "CJ Connection Step": "CJ > Products > Store Products > Unconnected > Connect/Add Automatic Connection",
      "Connection Status": "needs-cj-connection"
    },
    {
      "Product Handle": "sera-woven-table-runner",
      "Product Title": "Sera Woven Table Runner",
      "Product Status": "ACTIVE",
      "Shopify Product ID": "15796866548046",
      "Shopify Product GID": "gid://shopify/Product/15796866548046",
      "Shopify Admin URL": "https://admin.shopify.com/store/vre00g-8b/products/15796866548046",
      "CJ Source SKU": "CJYD239088001AZ",
      "CJ Product URL": "https://cjdropshipping.com/product/home-decoration-simple-woven-cotton-and-linen-table-runner-p-2506020359111604900.html",
      "Variant Title": "Wavy / 33 x 160 cm",
      "Variant SKU": "CM-CJYD239088001AZ-WAVY-33-X-160-CM",
      "Shopify Variant ID": "59516338504014",
      "Shopify Variant GID": "gid://shopify/ProductVariant/59516338504014",
      "Inventory Item ID": "57931506024782",
      "Inventory Item GID": "gid://shopify/InventoryItem/57931506024782",
      "Inventory Tracked": "FALSE",
      "Inventory Policy": "CONTINUE",
      "Option 1 Name": "Pattern",
      "Option 1 Value": "Wavy",
      "Option 2 Name": "Size",
      "Option 2 Value": "33 x 160 cm",
      "Option 3 Name": "",
      "Option 3 Value": "",
      "CJ Connection Step": "CJ > Products > Store Products > Unconnected > Connect/Add Automatic Connection",
      "Connection Status": "needs-cj-connection"
    },
    {
      "Product Handle": "sera-woven-table-runner",
      "Product Title": "Sera Woven Table Runner",
      "Product Status": "ACTIVE",
      "Shopify Product ID": "15796866548046",
      "Shopify Product GID": "gid://shopify/Product/15796866548046",
      "Shopify Admin URL": "https://admin.shopify.com/store/vre00g-8b/products/15796866548046",
      "CJ Source SKU": "CJYD239088001AZ",
      "CJ Product URL": "https://cjdropshipping.com/product/home-decoration-simple-woven-cotton-and-linen-table-runner-p-2506020359111604900.html",
      "Variant Title": "Wavy / 33 x 183 cm",
      "Variant SKU": "CM-CJYD239088001AZ-WAVY-33-X-183-CM",
      "Shopify Variant ID": "59516338536782",
      "Shopify Variant GID": "gid://shopify/ProductVariant/59516338536782",
      "Inventory Item ID": "57931506057550",
      "Inventory Item GID": "gid://shopify/InventoryItem/57931506057550",
      "Inventory Tracked": "FALSE",
      "Inventory Policy": "CONTINUE",
      "Option 1 Name": "Pattern",
      "Option 1 Value": "Wavy",
      "Option 2 Name": "Size",
      "Option 2 Value": "33 x 183 cm",
      "Option 3 Name": "",
      "Option 3 Value": "",
      "CJ Connection Step": "CJ > Products > Store Products > Unconnected > Connect/Add Automatic Connection",
      "Connection Status": "needs-cj-connection"
    },
    {
      "Product Handle": "sera-woven-table-runner",
      "Product Title": "Sera Woven Table Runner",
      "Product Status": "ACTIVE",
      "Shopify Product ID": "15796866548046",
      "Shopify Product GID": "gid://shopify/Product/15796866548046",
      "Shopify Admin URL": "https://admin.shopify.com/store/vre00g-8b/products/15796866548046",
      "CJ Source SKU": "CJYD239088001AZ",
      "CJ Product URL": "https://cjdropshipping.com/product/home-decoration-simple-woven-cotton-and-linen-table-runner-p-2506020359111604900.html",
      "Variant Title": "Wavy / 33 x 200 cm",
      "Variant SKU": "CM-CJYD239088001AZ-WAVY-33-X-200-CM",
      "Shopify Variant ID": "59516338569550",
      "Shopify Variant GID": "gid://shopify/ProductVariant/59516338569550",
      "Inventory Item ID": "57931506090318",
      "Inventory Item GID": "gid://shopify/InventoryItem/57931506090318",
      "Inventory Tracked": "FALSE",
      "Inventory Policy": "CONTINUE",
      "Option 1 Name": "Pattern",
      "Option 1 Value": "Wavy",
      "Option 2 Name": "Size",
      "Option 2 Value": "33 x 200 cm",
      "Option 3 Name": "",
      "Option 3 Value": "",
      "CJ Connection Step": "CJ > Products > Store Products > Unconnected > Connect/Add Automatic Connection",
      "Connection Status": "needs-cj-connection"
    },
    {
      "Product Handle": "sera-woven-table-runner",
      "Product Title": "Sera Woven Table Runner",
      "Product Status": "ACTIVE",
      "Shopify Product ID": "15796866548046",
      "Shopify Product GID": "gid://shopify/Product/15796866548046",
      "Shopify Admin URL": "https://admin.shopify.com/store/vre00g-8b/products/15796866548046",
      "CJ Source SKU": "CJYD239088001AZ",
      "CJ Product URL": "https://cjdropshipping.com/product/home-decoration-simple-woven-cotton-and-linen-table-runner-p-2506020359111604900.html",
      "Variant Title": "Beijing Hemp / 33 x 160 cm",
      "Variant SKU": "CM-CJYD239088001AZ-BEIJING-HEMP-33-X-160-CM",
      "Shopify Variant ID": "59516338602318",
      "Shopify Variant GID": "gid://shopify/ProductVariant/59516338602318",
      "Inventory Item ID": "57931506123086",
      "Inventory Item GID": "gid://shopify/InventoryItem/57931506123086",
      "Inventory Tracked": "FALSE",
      "Inventory Policy": "CONTINUE",
      "Option 1 Name": "Pattern",
      "Option 1 Value": "Beijing Hemp",
      "Option 2 Name": "Size",
      "Option 2 Value": "33 x 160 cm",
      "Option 3 Name": "",
      "Option 3 Value": "",
      "CJ Connection Step": "CJ > Products > Store Products > Unconnected > Connect/Add Automatic Connection",
      "Connection Status": "needs-cj-connection"
    },
    {
      "Product Handle": "sera-woven-table-runner",
      "Product Title": "Sera Woven Table Runner",
      "Product Status": "ACTIVE",
      "Shopify Product ID": "15796866548046",
      "Shopify Product GID": "gid://shopify/Product/15796866548046",
      "Shopify Admin URL": "https://admin.shopify.com/store/vre00g-8b/products/15796866548046",
      "CJ Source SKU": "CJYD239088001AZ",
      "CJ Product URL": "https://cjdropshipping.com/product/home-decoration-simple-woven-cotton-and-linen-table-runner-p-2506020359111604900.html",
      "Variant Title": "Beijing Hemp / 33 x 183 cm",
      "Variant SKU": "CM-CJYD239088001AZ-BEIJING-HEMP-33-X-183-CM",
      "Shopify Variant ID": "59516338635086",
      "Shopify Variant GID": "gid://shopify/ProductVariant/59516338635086",
      "Inventory Item ID": "57931506155854",
      "Inventory Item GID": "gid://shopify/InventoryItem/57931506155854",
      "Inventory Tracked": "FALSE",
      "Inventory Policy": "CONTINUE",
      "Option 1 Name": "Pattern",
      "Option 1 Value": "Beijing Hemp",
      "Option 2 Name": "Size",
      "Option 2 Value": "33 x 183 cm",
      "Option 3 Name": "",
      "Option 3 Value": "",
      "CJ Connection Step": "CJ > Products > Store Products > Unconnected > Connect/Add Automatic Connection",
      "Connection Status": "needs-cj-connection"
    },
    {
      "Product Handle": "sera-woven-table-runner",
      "Product Title": "Sera Woven Table Runner",
      "Product Status": "ACTIVE",
      "Shopify Product ID": "15796866548046",
      "Shopify Product GID": "gid://shopify/Product/15796866548046",
      "Shopify Admin URL": "https://admin.shopify.com/store/vre00g-8b/products/15796866548046",
      "CJ Source SKU": "CJYD239088001AZ",
      "CJ Product URL": "https://cjdropshipping.com/product/home-decoration-simple-woven-cotton-and-linen-table-runner-p-2506020359111604900.html",
      "Variant Title": "Beijing Hemp / 33 x 200 cm",
      "Variant SKU": "CM-CJYD239088001AZ-BEIJING-HEMP-33-X-200-CM",
      "Shopify Variant ID": "59516338667854",
      "Shopify Variant GID": "gid://shopify/ProductVariant/59516338667854",
      "Inventory Item ID": "57931506188622",
      "Inventory Item GID": "gid://shopify/InventoryItem/57931506188622",
      "Inventory Tracked": "FALSE",
      "Inventory Policy": "CONTINUE",
      "Option 1 Name": "Pattern",
      "Option 1 Value": "Beijing Hemp",
      "Option 2 Name": "Size",
      "Option 2 Value": "33 x 200 cm",
      "Option 3 Name": "",
      "Option 3 Value": "",
      "CJ Connection Step": "CJ > Products > Store Products > Unconnected > Connect/Add Automatic Connection",
      "Connection Status": "needs-cj-connection"
    },
    {
      "Product Handle": "sol-linen-cushion-cover",
      "Product Title": "Sol Linen Cushion Cover",
      "Product Status": "ACTIVE",
      "Shopify Product ID": "15796866679118",
      "Shopify Product GID": "gid://shopify/Product/15796866679118",
      "Shopify Admin URL": "https://admin.shopify.com/store/vre00g-8b/products/15796866679118",
      "CJ Source SKU": "CJZT102408801AZ",
      "CJ Product URL": "https://www.cjdropshipping.com/product/solid-color-linen-sofa-pillow-cushion-living-room-pillow-cover-p-1365950473881915392.html",
      "Variant Title": "Light Grey",
      "Variant SKU": "CM-CJZT102408801AZ-LIGHT-GREY",
      "Shopify Variant ID": "59516339585358",
      "Shopify Variant GID": "gid://shopify/ProductVariant/59516339585358",
      "Inventory Item ID": "57931507106126",
      "Inventory Item GID": "gid://shopify/InventoryItem/57931507106126",
      "Inventory Tracked": "FALSE",
      "Inventory Policy": "CONTINUE",
      "Option 1 Name": "Color",
      "Option 1 Value": "Light Grey",
      "Option 2 Name": "",
      "Option 2 Value": "",
      "Option 3 Name": "",
      "Option 3 Value": "",
      "CJ Connection Step": "CJ > Products > Store Products > Unconnected > Connect/Add Automatic Connection",
      "Connection Status": "needs-cj-connection"
    },
    {
      "Product Handle": "sol-linen-cushion-cover",
      "Product Title": "Sol Linen Cushion Cover",
      "Product Status": "ACTIVE",
      "Shopify Product ID": "15796866679118",
      "Shopify Product GID": "gid://shopify/Product/15796866679118",
      "Shopify Admin URL": "https://admin.shopify.com/store/vre00g-8b/products/15796866679118",
      "CJ Source SKU": "CJZT102408801AZ",
      "CJ Product URL": "https://www.cjdropshipping.com/product/solid-color-linen-sofa-pillow-cushion-living-room-pillow-cover-p-1365950473881915392.html",
      "Variant Title": "Khaki",
      "Variant SKU": "CM-CJZT102408801AZ-KHAKI",
      "Shopify Variant ID": "59516339618126",
      "Shopify Variant GID": "gid://shopify/ProductVariant/59516339618126",
      "Inventory Item ID": "57931507138894",
      "Inventory Item GID": "gid://shopify/InventoryItem/57931507138894",
      "Inventory Tracked": "FALSE",
      "Inventory Policy": "CONTINUE",
      "Option 1 Name": "Color",
      "Option 1 Value": "Khaki",
      "Option 2 Name": "",
      "Option 2 Value": "",
      "Option 3 Name": "",
      "Option 3 Value": "",
      "CJ Connection Step": "CJ > Products > Store Products > Unconnected > Connect/Add Automatic Connection",
      "Connection Status": "needs-cj-connection"
    },
    {
      "Product Handle": "sol-linen-cushion-cover",
      "Product Title": "Sol Linen Cushion Cover",
      "Product Status": "ACTIVE",
      "Shopify Product ID": "15796866679118",
      "Shopify Product GID": "gid://shopify/Product/15796866679118",
      "Shopify Admin URL": "https://admin.shopify.com/store/vre00g-8b/products/15796866679118",
      "CJ Source SKU": "CJZT102408801AZ",
      "CJ Product URL": "https://www.cjdropshipping.com/product/solid-color-linen-sofa-pillow-cushion-living-room-pillow-cover-p-1365950473881915392.html",
      "Variant Title": "Coffee",
      "Variant SKU": "CM-CJZT102408801AZ-COFFEE",
      "Shopify Variant ID": "59516339650894",
      "Shopify Variant GID": "gid://shopify/ProductVariant/59516339650894",
      "Inventory Item ID": "57931507171662",
      "Inventory Item GID": "gid://shopify/InventoryItem/57931507171662",
      "Inventory Tracked": "FALSE",
      "Inventory Policy": "CONTINUE",
      "Option 1 Name": "Color",
      "Option 1 Value": "Coffee",
      "Option 2 Name": "",
      "Option 2 Value": "",
      "Option 3 Name": "",
      "Option 3 Value": "",
      "CJ Connection Step": "CJ > Products > Store Products > Unconnected > Connect/Add Automatic Connection",
      "Connection Status": "needs-cj-connection"
    },
    {
      "Product Handle": "sol-linen-cushion-cover",
      "Product Title": "Sol Linen Cushion Cover",
      "Product Status": "ACTIVE",
      "Shopify Product ID": "15796866679118",
      "Shopify Product GID": "gid://shopify/Product/15796866679118",
      "Shopify Admin URL": "https://admin.shopify.com/store/vre00g-8b/products/15796866679118",
      "CJ Source SKU": "CJZT102408801AZ",
      "CJ Product URL": "https://www.cjdropshipping.com/product/solid-color-linen-sofa-pillow-cushion-living-room-pillow-cover-p-1365950473881915392.html",
      "Variant Title": "Green",
      "Variant SKU": "CM-CJZT102408801AZ-GREEN",
      "Shopify Variant ID": "59516339683662",
      "Shopify Variant GID": "gid://shopify/ProductVariant/59516339683662",
      "Inventory Item ID": "57931507204430",
      "Inventory Item GID": "gid://shopify/InventoryItem/57931507204430",
      "Inventory Tracked": "FALSE",
      "Inventory Policy": "CONTINUE",
      "Option 1 Name": "Color",
      "Option 1 Value": "Green",
      "Option 2 Name": "",
      "Option 2 Value": "",
      "Option 3 Name": "",
      "Option 3 Value": "",
      "CJ Connection Step": "CJ > Products > Store Products > Unconnected > Connect/Add Automatic Connection",
      "Connection Status": "needs-cj-connection"
    },
    {
      "Product Handle": "alba-cotton-linen-cushion",
      "Product Title": "Alba Cotton-Linen Cushion",
      "Product Status": "ACTIVE",
      "Shopify Product ID": "15796866777422",
      "Shopify Product GID": "gid://shopify/Product/15796866777422",
      "Shopify Admin URL": "https://admin.shopify.com/store/vre00g-8b/products/15796866777422",
      "CJ Source SKU": "CJZT113551601AZ",
      "CJ Product URL": "https://cjdropshipping.com/product/plain-cotton-linen-sofa-cushion-thickened-square-pillow-p-1394921392557920256.html",
      "Variant Title": "Beige / Pillowcase",
      "Variant SKU": "CM-CJZT113551601AZ-BEIGE-PILLOWCASE",
      "Shopify Variant ID": "59516343648590",
      "Shopify Variant GID": "gid://shopify/ProductVariant/59516343648590",
      "Inventory Item ID": "57931511169358",
      "Inventory Item GID": "gid://shopify/InventoryItem/57931511169358",
      "Inventory Tracked": "FALSE",
      "Inventory Policy": "CONTINUE",
      "Option 1 Name": "Color",
      "Option 1 Value": "Beige",
      "Option 2 Name": "Style",
      "Option 2 Value": "Pillowcase",
      "Option 3 Name": "",
      "Option 3 Value": "",
      "CJ Connection Step": "CJ > Products > Store Products > Unconnected > Connect/Add Automatic Connection",
      "Connection Status": "needs-cj-connection"
    },
    {
      "Product Handle": "alba-cotton-linen-cushion",
      "Product Title": "Alba Cotton-Linen Cushion",
      "Product Status": "ACTIVE",
      "Shopify Product ID": "15796866777422",
      "Shopify Product GID": "gid://shopify/Product/15796866777422",
      "Shopify Admin URL": "https://admin.shopify.com/store/vre00g-8b/products/15796866777422",
      "CJ Source SKU": "CJZT113551601AZ",
      "CJ Product URL": "https://cjdropshipping.com/product/plain-cotton-linen-sofa-cushion-thickened-square-pillow-p-1394921392557920256.html",
      "Variant Title": "Beige / Pillow with insert",
      "Variant SKU": "CM-CJZT113551601AZ-BEIGE-PILLOW-WITH-INSERT",
      "Shopify Variant ID": "59516343681358",
      "Shopify Variant GID": "gid://shopify/ProductVariant/59516343681358",
      "Inventory Item ID": "57931511202126",
      "Inventory Item GID": "gid://shopify/InventoryItem/57931511202126",
      "Inventory Tracked": "FALSE",
      "Inventory Policy": "CONTINUE",
      "Option 1 Name": "Color",
      "Option 1 Value": "Beige",
      "Option 2 Name": "Style",
      "Option 2 Value": "Pillow with insert",
      "Option 3 Name": "",
      "Option 3 Value": "",
      "CJ Connection Step": "CJ > Products > Store Products > Unconnected > Connect/Add Automatic Connection",
      "Connection Status": "needs-cj-connection"
    },
    {
      "Product Handle": "alba-cotton-linen-cushion",
      "Product Title": "Alba Cotton-Linen Cushion",
      "Product Status": "ACTIVE",
      "Shopify Product ID": "15796866777422",
      "Shopify Product GID": "gid://shopify/Product/15796866777422",
      "Shopify Admin URL": "https://admin.shopify.com/store/vre00g-8b/products/15796866777422",
      "CJ Source SKU": "CJZT113551601AZ",
      "CJ Product URL": "https://cjdropshipping.com/product/plain-cotton-linen-sofa-cushion-thickened-square-pillow-p-1394921392557920256.html",
      "Variant Title": "Khaki / Pillowcase",
      "Variant SKU": "CM-CJZT113551601AZ-KHAKI-PILLOWCASE",
      "Shopify Variant ID": "59516343714126",
      "Shopify Variant GID": "gid://shopify/ProductVariant/59516343714126",
      "Inventory Item ID": "57931511234894",
      "Inventory Item GID": "gid://shopify/InventoryItem/57931511234894",
      "Inventory Tracked": "FALSE",
      "Inventory Policy": "CONTINUE",
      "Option 1 Name": "Color",
      "Option 1 Value": "Khaki",
      "Option 2 Name": "Style",
      "Option 2 Value": "Pillowcase",
      "Option 3 Name": "",
      "Option 3 Value": "",
      "CJ Connection Step": "CJ > Products > Store Products > Unconnected > Connect/Add Automatic Connection",
      "Connection Status": "needs-cj-connection"
    },
    {
      "Product Handle": "alba-cotton-linen-cushion",
      "Product Title": "Alba Cotton-Linen Cushion",
      "Product Status": "ACTIVE",
      "Shopify Product ID": "15796866777422",
      "Shopify Product GID": "gid://shopify/Product/15796866777422",
      "Shopify Admin URL": "https://admin.shopify.com/store/vre00g-8b/products/15796866777422",
      "CJ Source SKU": "CJZT113551601AZ",
      "CJ Product URL": "https://cjdropshipping.com/product/plain-cotton-linen-sofa-cushion-thickened-square-pillow-p-1394921392557920256.html",
      "Variant Title": "Khaki / Pillow with insert",
      "Variant SKU": "CM-CJZT113551601AZ-KHAKI-PILLOW-WITH-INSERT",
      "Shopify Variant ID": "59516343746894",
      "Shopify Variant GID": "gid://shopify/ProductVariant/59516343746894",
      "Inventory Item ID": "57931511267662",
      "Inventory Item GID": "gid://shopify/InventoryItem/57931511267662",
      "Inventory Tracked": "FALSE",
      "Inventory Policy": "CONTINUE",
      "Option 1 Name": "Color",
      "Option 1 Value": "Khaki",
      "Option 2 Name": "Style",
      "Option 2 Value": "Pillow with insert",
      "Option 3 Name": "",
      "Option 3 Value": "",
      "CJ Connection Step": "CJ > Products > Store Products > Unconnected > Connect/Add Automatic Connection",
      "Connection Status": "needs-cj-connection"
    },
    {
      "Product Handle": "alba-cotton-linen-cushion",
      "Product Title": "Alba Cotton-Linen Cushion",
      "Product Status": "ACTIVE",
      "Shopify Product ID": "15796866777422",
      "Shopify Product GID": "gid://shopify/Product/15796866777422",
      "Shopify Admin URL": "https://admin.shopify.com/store/vre00g-8b/products/15796866777422",
      "CJ Source SKU": "CJZT113551601AZ",
      "CJ Product URL": "https://cjdropshipping.com/product/plain-cotton-linen-sofa-cushion-thickened-square-pillow-p-1394921392557920256.html",
      "Variant Title": "Grey / Pillowcase",
      "Variant SKU": "CM-CJZT113551601AZ-GREY-PILLOWCASE",
      "Shopify Variant ID": "59516343779662",
      "Shopify Variant GID": "gid://shopify/ProductVariant/59516343779662",
      "Inventory Item ID": "57931511300430",
      "Inventory Item GID": "gid://shopify/InventoryItem/57931511300430",
      "Inventory Tracked": "FALSE",
      "Inventory Policy": "CONTINUE",
      "Option 1 Name": "Color",
      "Option 1 Value": "Grey",
      "Option 2 Name": "Style",
      "Option 2 Value": "Pillowcase",
      "Option 3 Name": "",
      "Option 3 Value": "",
      "CJ Connection Step": "CJ > Products > Store Products > Unconnected > Connect/Add Automatic Connection",
      "Connection Status": "needs-cj-connection"
    },
    {
      "Product Handle": "alba-cotton-linen-cushion",
      "Product Title": "Alba Cotton-Linen Cushion",
      "Product Status": "ACTIVE",
      "Shopify Product ID": "15796866777422",
      "Shopify Product GID": "gid://shopify/Product/15796866777422",
      "Shopify Admin URL": "https://admin.shopify.com/store/vre00g-8b/products/15796866777422",
      "CJ Source SKU": "CJZT113551601AZ",
      "CJ Product URL": "https://cjdropshipping.com/product/plain-cotton-linen-sofa-cushion-thickened-square-pillow-p-1394921392557920256.html",
      "Variant Title": "Grey / Pillow with insert",
      "Variant SKU": "CM-CJZT113551601AZ-GREY-PILLOW-WITH-INSERT",
      "Shopify Variant ID": "59516343812430",
      "Shopify Variant GID": "gid://shopify/ProductVariant/59516343812430",
      "Inventory Item ID": "57931511333198",
      "Inventory Item GID": "gid://shopify/InventoryItem/57931511333198",
      "Inventory Tracked": "FALSE",
      "Inventory Policy": "CONTINUE",
      "Option 1 Name": "Color",
      "Option 1 Value": "Grey",
      "Option 2 Name": "Style",
      "Option 2 Value": "Pillow with insert",
      "Option 3 Name": "",
      "Option 3 Value": "",
      "CJ Connection Step": "CJ > Products > Store Products > Unconnected > Connect/Add Automatic Connection",
      "Connection Status": "needs-cj-connection"
    },
    {
      "Product Handle": "vale-walnut-storage-tray",
      "Product Title": "Vale Walnut Storage Tray",
      "Product Status": "ACTIVE",
      "Shopify Product ID": "15796866810190",
      "Shopify Product GID": "gid://shopify/Product/15796866810190",
      "Shopify Admin URL": "https://admin.shopify.com/store/vre00g-8b/products/15796866810190",
      "CJ Source SKU": "CJYD231130901AZ",
      "CJ Product URL": "https://cjdropshipping.com/product/household-fruit-plate-wooden-storage-tray-p-2502280831271616600.html",
      "Variant Title": "14 x 14 x 3.3 cm",
      "Variant SKU": "CM-CJYD231130901AZ-14-X-14-X-3-3-CM",
      "Shopify Variant ID": "59516343845198",
      "Shopify Variant GID": "gid://shopify/ProductVariant/59516343845198",
      "Inventory Item ID": "57931511365966",
      "Inventory Item GID": "gid://shopify/InventoryItem/57931511365966",
      "Inventory Tracked": "FALSE",
      "Inventory Policy": "CONTINUE",
      "Option 1 Name": "Size",
      "Option 1 Value": "14 x 14 x 3.3 cm",
      "Option 2 Name": "",
      "Option 2 Value": "",
      "Option 3 Name": "",
      "Option 3 Value": "",
      "CJ Connection Step": "CJ > Products > Store Products > Unconnected > Connect/Add Automatic Connection",
      "Connection Status": "needs-cj-connection"
    },
    {
      "Product Handle": "vale-walnut-storage-tray",
      "Product Title": "Vale Walnut Storage Tray",
      "Product Status": "ACTIVE",
      "Shopify Product ID": "15796866810190",
      "Shopify Product GID": "gid://shopify/Product/15796866810190",
      "Shopify Admin URL": "https://admin.shopify.com/store/vre00g-8b/products/15796866810190",
      "CJ Source SKU": "CJYD231130901AZ",
      "CJ Product URL": "https://cjdropshipping.com/product/household-fruit-plate-wooden-storage-tray-p-2502280831271616600.html",
      "Variant Title": "28 x 14 x 3.3 cm",
      "Variant SKU": "CM-CJYD231130901AZ-28-X-14-X-3-3-CM",
      "Shopify Variant ID": "59516343877966",
      "Shopify Variant GID": "gid://shopify/ProductVariant/59516343877966",
      "Inventory Item ID": "57931511398734",
      "Inventory Item GID": "gid://shopify/InventoryItem/57931511398734",
      "Inventory Tracked": "FALSE",
      "Inventory Policy": "CONTINUE",
      "Option 1 Name": "Size",
      "Option 1 Value": "28 x 14 x 3.3 cm",
      "Option 2 Name": "",
      "Option 2 Value": "",
      "Option 3 Name": "",
      "Option 3 Value": "",
      "CJ Connection Step": "CJ > Products > Store Products > Unconnected > Connect/Add Automatic Connection",
      "Connection Status": "needs-cj-connection"
    },
    {
      "Product Handle": "vale-walnut-storage-tray",
      "Product Title": "Vale Walnut Storage Tray",
      "Product Status": "ACTIVE",
      "Shopify Product ID": "15796866810190",
      "Shopify Product GID": "gid://shopify/Product/15796866810190",
      "Shopify Admin URL": "https://admin.shopify.com/store/vre00g-8b/products/15796866810190",
      "CJ Source SKU": "CJYD231130901AZ",
      "CJ Product URL": "https://cjdropshipping.com/product/household-fruit-plate-wooden-storage-tray-p-2502280831271616600.html",
      "Variant Title": "42 x 14 x 3.3 cm",
      "Variant SKU": "CM-CJYD231130901AZ-42-X-14-X-3-3-CM",
      "Shopify Variant ID": "59516343910734",
      "Shopify Variant GID": "gid://shopify/ProductVariant/59516343910734",
      "Inventory Item ID": "57931511431502",
      "Inventory Item GID": "gid://shopify/InventoryItem/57931511431502",
      "Inventory Tracked": "FALSE",
      "Inventory Policy": "CONTINUE",
      "Option 1 Name": "Size",
      "Option 1 Value": "42 x 14 x 3.3 cm",
      "Option 2 Name": "",
      "Option 2 Value": "",
      "Option 3 Name": "",
      "Option 3 Value": "",
      "CJ Connection Step": "CJ > Products > Store Products > Unconnected > Connect/Add Automatic Connection",
      "Connection Status": "needs-cj-connection"
    },
    {
      "Product Handle": "ayla-cotton-bath-towel",
      "Product Title": "Ayla Cotton Bath Towel",
      "Product Status": "ACTIVE",
      "Shopify Product ID": "15797127577934",
      "Shopify Product GID": "gid://shopify/Product/15797127577934",
      "Shopify Admin URL": "https://admin.shopify.com/store/vre00g-8b/products/15797127577934",
      "CJ Source SKU": "CJJJJFMJ00217",
      "CJ Product URL": "https://cjdropshipping.com/product/pure-cotton-bath-towel-p-0F71F755-035C-49CE-9E54-8103862C06AE.html",
      "Variant Title": "Beige",
      "Variant SKU": "CM-CJJJJFMJ00217-BEIGE",
      "Shopify Variant ID": "59517358899534",
      "Shopify Variant GID": "gid://shopify/ProductVariant/59517358899534",
      "Inventory Item ID": "57932563185998",
      "Inventory Item GID": "gid://shopify/InventoryItem/57932563185998",
      "Inventory Tracked": "FALSE",
      "Inventory Policy": "CONTINUE",
      "Option 1 Name": "Color",
      "Option 1 Value": "Beige",
      "Option 2 Name": "",
      "Option 2 Value": "",
      "Option 3 Name": "",
      "Option 3 Value": "",
      "CJ Connection Step": "CJ > Products > Store Products > Unconnected > Connect/Add Automatic Connection",
      "Connection Status": "needs-cj-connection"
    },
    {
      "Product Handle": "ayla-cotton-bath-towel",
      "Product Title": "Ayla Cotton Bath Towel",
      "Product Status": "ACTIVE",
      "Shopify Product ID": "15797127577934",
      "Shopify Product GID": "gid://shopify/Product/15797127577934",
      "Shopify Admin URL": "https://admin.shopify.com/store/vre00g-8b/products/15797127577934",
      "CJ Source SKU": "CJJJJFMJ00217",
      "CJ Product URL": "https://cjdropshipping.com/product/pure-cotton-bath-towel-p-0F71F755-035C-49CE-9E54-8103862C06AE.html",
      "Variant Title": "Khaki",
      "Variant SKU": "CM-CJJJJFMJ00217-KHAKI",
      "Shopify Variant ID": "59517358932302",
      "Shopify Variant GID": "gid://shopify/ProductVariant/59517358932302",
      "Inventory Item ID": "57932563218766",
      "Inventory Item GID": "gid://shopify/InventoryItem/57932563218766",
      "Inventory Tracked": "FALSE",
      "Inventory Policy": "CONTINUE",
      "Option 1 Name": "Color",
      "Option 1 Value": "Khaki",
      "Option 2 Name": "",
      "Option 2 Value": "",
      "Option 3 Name": "",
      "Option 3 Value": "",
      "CJ Connection Step": "CJ > Products > Store Products > Unconnected > Connect/Add Automatic Connection",
      "Connection Status": "needs-cj-connection"
    },
    {
      "Product Handle": "ayla-cotton-bath-towel",
      "Product Title": "Ayla Cotton Bath Towel",
      "Product Status": "ACTIVE",
      "Shopify Product ID": "15797127577934",
      "Shopify Product GID": "gid://shopify/Product/15797127577934",
      "Shopify Admin URL": "https://admin.shopify.com/store/vre00g-8b/products/15797127577934",
      "CJ Source SKU": "CJJJJFMJ00217",
      "CJ Product URL": "https://cjdropshipping.com/product/pure-cotton-bath-towel-p-0F71F755-035C-49CE-9E54-8103862C06AE.html",
      "Variant Title": "Light Brown",
      "Variant SKU": "CM-CJJJJFMJ00217-LIGHT-BROWN",
      "Shopify Variant ID": "59517358965070",
      "Shopify Variant GID": "gid://shopify/ProductVariant/59517358965070",
      "Inventory Item ID": "57932563251534",
      "Inventory Item GID": "gid://shopify/InventoryItem/57932563251534",
      "Inventory Tracked": "FALSE",
      "Inventory Policy": "CONTINUE",
      "Option 1 Name": "Color",
      "Option 1 Value": "Light Brown",
      "Option 2 Name": "",
      "Option 2 Value": "",
      "Option 3 Name": "",
      "Option 3 Value": "",
      "CJ Connection Step": "CJ > Products > Store Products > Unconnected > Connect/Add Automatic Connection",
      "Connection Status": "needs-cj-connection"
    },
    {
      "Product Handle": "ayla-cotton-bath-towel",
      "Product Title": "Ayla Cotton Bath Towel",
      "Product Status": "ACTIVE",
      "Shopify Product ID": "15797127577934",
      "Shopify Product GID": "gid://shopify/Product/15797127577934",
      "Shopify Admin URL": "https://admin.shopify.com/store/vre00g-8b/products/15797127577934",
      "CJ Source SKU": "CJJJJFMJ00217",
      "CJ Product URL": "https://cjdropshipping.com/product/pure-cotton-bath-towel-p-0F71F755-035C-49CE-9E54-8103862C06AE.html",
      "Variant Title": "Dark Brown",
      "Variant SKU": "CM-CJJJJFMJ00217-DARK-BROWN",
      "Shopify Variant ID": "59517358997838",
      "Shopify Variant GID": "gid://shopify/ProductVariant/59517358997838",
      "Inventory Item ID": "57932563284302",
      "Inventory Item GID": "gid://shopify/InventoryItem/57932563284302",
      "Inventory Tracked": "FALSE",
      "Inventory Policy": "CONTINUE",
      "Option 1 Name": "Color",
      "Option 1 Value": "Dark Brown",
      "Option 2 Name": "",
      "Option 2 Value": "",
      "Option 3 Name": "",
      "Option 3 Value": "",
      "CJ Connection Step": "CJ > Products > Store Products > Unconnected > Connect/Add Automatic Connection",
      "Connection Status": "needs-cj-connection"
    },
    {
      "Product Handle": "mara-linen-dining-placemat",
      "Product Title": "Mara Linen Dining Placemat",
      "Product Status": "ACTIVE",
      "Shopify Product ID": "15797127610702",
      "Shopify Product GID": "gid://shopify/Product/15797127610702",
      "Shopify Admin URL": "https://admin.shopify.com/store/vre00g-8b/products/15797127610702",
      "CJ Source SKU": "CJYD206843001AZ",
      "CJ Product URL": "https://cjdropshipping.com/product/linen-dining-table-cover-heat-insulation-and-anti-scald-p-2406250742051603200.html",
      "Variant Title": "Off White",
      "Variant SKU": "CM-CJYD206843001AZ-OFF-WHITE",
      "Shopify Variant ID": "59517359030606",
      "Shopify Variant GID": "gid://shopify/ProductVariant/59517359030606",
      "Inventory Item ID": "57932563317070",
      "Inventory Item GID": "gid://shopify/InventoryItem/57932563317070",
      "Inventory Tracked": "FALSE",
      "Inventory Policy": "CONTINUE",
      "Option 1 Name": "Color",
      "Option 1 Value": "Off White",
      "Option 2 Name": "",
      "Option 2 Value": "",
      "Option 3 Name": "",
      "Option 3 Value": "",
      "CJ Connection Step": "CJ > Products > Store Products > Unconnected > Connect/Add Automatic Connection",
      "Connection Status": "needs-cj-connection"
    },
    {
      "Product Handle": "mara-linen-dining-placemat",
      "Product Title": "Mara Linen Dining Placemat",
      "Product Status": "ACTIVE",
      "Shopify Product ID": "15797127610702",
      "Shopify Product GID": "gid://shopify/Product/15797127610702",
      "Shopify Admin URL": "https://admin.shopify.com/store/vre00g-8b/products/15797127610702",
      "CJ Source SKU": "CJYD206843001AZ",
      "CJ Product URL": "https://cjdropshipping.com/product/linen-dining-table-cover-heat-insulation-and-anti-scald-p-2406250742051603200.html",
      "Variant Title": "Khaki",
      "Variant SKU": "CM-CJYD206843001AZ-KHAKI",
      "Shopify Variant ID": "59517359063374",
      "Shopify Variant GID": "gid://shopify/ProductVariant/59517359063374",
      "Inventory Item ID": "57932563349838",
      "Inventory Item GID": "gid://shopify/InventoryItem/57932563349838",
      "Inventory Tracked": "FALSE",
      "Inventory Policy": "CONTINUE",
      "Option 1 Name": "Color",
      "Option 1 Value": "Khaki",
      "Option 2 Name": "",
      "Option 2 Value": "",
      "Option 3 Name": "",
      "Option 3 Value": "",
      "CJ Connection Step": "CJ > Products > Store Products > Unconnected > Connect/Add Automatic Connection",
      "Connection Status": "needs-cj-connection"
    },
    {
      "Product Handle": "mara-linen-dining-placemat",
      "Product Title": "Mara Linen Dining Placemat",
      "Product Status": "ACTIVE",
      "Shopify Product ID": "15797127610702",
      "Shopify Product GID": "gid://shopify/Product/15797127610702",
      "Shopify Admin URL": "https://admin.shopify.com/store/vre00g-8b/products/15797127610702",
      "CJ Source SKU": "CJYD206843001AZ",
      "CJ Product URL": "https://cjdropshipping.com/product/linen-dining-table-cover-heat-insulation-and-anti-scald-p-2406250742051603200.html",
      "Variant Title": "Light Brown",
      "Variant SKU": "CM-CJYD206843001AZ-LIGHT-BROWN",
      "Shopify Variant ID": "59517359096142",
      "Shopify Variant GID": "gid://shopify/ProductVariant/59517359096142",
      "Inventory Item ID": "57932563382606",
      "Inventory Item GID": "gid://shopify/InventoryItem/57932563382606",
      "Inventory Tracked": "FALSE",
      "Inventory Policy": "CONTINUE",
      "Option 1 Name": "Color",
      "Option 1 Value": "Light Brown",
      "Option 2 Name": "",
      "Option 2 Value": "",
      "Option 3 Name": "",
      "Option 3 Value": "",
      "CJ Connection Step": "CJ > Products > Store Products > Unconnected > Connect/Add Automatic Connection",
      "Connection Status": "needs-cj-connection"
    },
    {
      "Product Handle": "mara-linen-dining-placemat",
      "Product Title": "Mara Linen Dining Placemat",
      "Product Status": "ACTIVE",
      "Shopify Product ID": "15797127610702",
      "Shopify Product GID": "gid://shopify/Product/15797127610702",
      "Shopify Admin URL": "https://admin.shopify.com/store/vre00g-8b/products/15797127610702",
      "CJ Source SKU": "CJYD206843001AZ",
      "CJ Product URL": "https://cjdropshipping.com/product/linen-dining-table-cover-heat-insulation-and-anti-scald-p-2406250742051603200.html",
      "Variant Title": "Dark Coffee",
      "Variant SKU": "CM-CJYD206843001AZ-DARK-COFFEE",
      "Shopify Variant ID": "59517359128910",
      "Shopify Variant GID": "gid://shopify/ProductVariant/59517359128910",
      "Inventory Item ID": "57932563415374",
      "Inventory Item GID": "gid://shopify/InventoryItem/57932563415374",
      "Inventory Tracked": "FALSE",
      "Inventory Policy": "CONTINUE",
      "Option 1 Name": "Color",
      "Option 1 Value": "Dark Coffee",
      "Option 2 Name": "",
      "Option 2 Value": "",
      "Option 3 Name": "",
      "Option 3 Value": "",
      "CJ Connection Step": "CJ > Products > Store Products > Unconnected > Connect/Add Automatic Connection",
      "Connection Status": "needs-cj-connection"
    },
    {
      "Product Handle": "nora-round-cotton-trivet",
      "Product Title": "Nora Round Cotton Trivet",
      "Product Status": "ACTIVE",
      "Shopify Product ID": "15797127643470",
      "Shopify Product GID": "gid://shopify/Product/15797127643470",
      "Shopify Admin URL": "https://admin.shopify.com/store/vre00g-8b/products/15797127643470",
      "CJ Source SKU": "CJYD206667601AZ",
      "CJ Product URL": "https://cjdropshipping.com/product/home-dining-table-coaster-western-style-placemat-p-2406230620351620400.html",
      "Variant Title": "Type A / 18 cm",
      "Variant SKU": "CM-CJYD206667601AZ-TYPE-A-18-CM",
      "Shopify Variant ID": "59517359161678",
      "Shopify Variant GID": "gid://shopify/ProductVariant/59517359161678",
      "Inventory Item ID": "57932563448142",
      "Inventory Item GID": "gid://shopify/InventoryItem/57932563448142",
      "Inventory Tracked": "FALSE",
      "Inventory Policy": "CONTINUE",
      "Option 1 Name": "Style",
      "Option 1 Value": "Type A",
      "Option 2 Name": "Size",
      "Option 2 Value": "18 cm",
      "Option 3 Name": "",
      "Option 3 Value": "",
      "CJ Connection Step": "CJ > Products > Store Products > Unconnected > Connect/Add Automatic Connection",
      "Connection Status": "needs-cj-connection"
    },
    {
      "Product Handle": "nora-round-cotton-trivet",
      "Product Title": "Nora Round Cotton Trivet",
      "Product Status": "ACTIVE",
      "Shopify Product ID": "15797127643470",
      "Shopify Product GID": "gid://shopify/Product/15797127643470",
      "Shopify Admin URL": "https://admin.shopify.com/store/vre00g-8b/products/15797127643470",
      "CJ Source SKU": "CJYD206667601AZ",
      "CJ Product URL": "https://cjdropshipping.com/product/home-dining-table-coaster-western-style-placemat-p-2406230620351620400.html",
      "Variant Title": "Type A / 24 cm",
      "Variant SKU": "CM-CJYD206667601AZ-TYPE-A-24-CM",
      "Shopify Variant ID": "59517359194446",
      "Shopify Variant GID": "gid://shopify/ProductVariant/59517359194446",
      "Inventory Item ID": "57932563480910",
      "Inventory Item GID": "gid://shopify/InventoryItem/57932563480910",
      "Inventory Tracked": "FALSE",
      "Inventory Policy": "CONTINUE",
      "Option 1 Name": "Style",
      "Option 1 Value": "Type A",
      "Option 2 Name": "Size",
      "Option 2 Value": "24 cm",
      "Option 3 Name": "",
      "Option 3 Value": "",
      "CJ Connection Step": "CJ > Products > Store Products > Unconnected > Connect/Add Automatic Connection",
      "Connection Status": "needs-cj-connection"
    },
    {
      "Product Handle": "nora-round-cotton-trivet",
      "Product Title": "Nora Round Cotton Trivet",
      "Product Status": "ACTIVE",
      "Shopify Product ID": "15797127643470",
      "Shopify Product GID": "gid://shopify/Product/15797127643470",
      "Shopify Admin URL": "https://admin.shopify.com/store/vre00g-8b/products/15797127643470",
      "CJ Source SKU": "CJYD206667601AZ",
      "CJ Product URL": "https://cjdropshipping.com/product/home-dining-table-coaster-western-style-placemat-p-2406230620351620400.html",
      "Variant Title": "Type A / 30 cm",
      "Variant SKU": "CM-CJYD206667601AZ-TYPE-A-30-CM",
      "Shopify Variant ID": "59517359227214",
      "Shopify Variant GID": "gid://shopify/ProductVariant/59517359227214",
      "Inventory Item ID": "57932563513678",
      "Inventory Item GID": "gid://shopify/InventoryItem/57932563513678",
      "Inventory Tracked": "FALSE",
      "Inventory Policy": "CONTINUE",
      "Option 1 Name": "Style",
      "Option 1 Value": "Type A",
      "Option 2 Name": "Size",
      "Option 2 Value": "30 cm",
      "Option 3 Name": "",
      "Option 3 Value": "",
      "CJ Connection Step": "CJ > Products > Store Products > Unconnected > Connect/Add Automatic Connection",
      "Connection Status": "needs-cj-connection"
    },
    {
      "Product Handle": "nora-round-cotton-trivet",
      "Product Title": "Nora Round Cotton Trivet",
      "Product Status": "ACTIVE",
      "Shopify Product ID": "15797127643470",
      "Shopify Product GID": "gid://shopify/Product/15797127643470",
      "Shopify Admin URL": "https://admin.shopify.com/store/vre00g-8b/products/15797127643470",
      "CJ Source SKU": "CJYD206667601AZ",
      "CJ Product URL": "https://cjdropshipping.com/product/home-dining-table-coaster-western-style-placemat-p-2406230620351620400.html",
      "Variant Title": "Type B / 18 cm",
      "Variant SKU": "CM-CJYD206667601AZ-TYPE-B-18-CM",
      "Shopify Variant ID": "59517359259982",
      "Shopify Variant GID": "gid://shopify/ProductVariant/59517359259982",
      "Inventory Item ID": "57932563546446",
      "Inventory Item GID": "gid://shopify/InventoryItem/57932563546446",
      "Inventory Tracked": "FALSE",
      "Inventory Policy": "CONTINUE",
      "Option 1 Name": "Style",
      "Option 1 Value": "Type B",
      "Option 2 Name": "Size",
      "Option 2 Value": "18 cm",
      "Option 3 Name": "",
      "Option 3 Value": "",
      "CJ Connection Step": "CJ > Products > Store Products > Unconnected > Connect/Add Automatic Connection",
      "Connection Status": "needs-cj-connection"
    },
    {
      "Product Handle": "nora-round-cotton-trivet",
      "Product Title": "Nora Round Cotton Trivet",
      "Product Status": "ACTIVE",
      "Shopify Product ID": "15797127643470",
      "Shopify Product GID": "gid://shopify/Product/15797127643470",
      "Shopify Admin URL": "https://admin.shopify.com/store/vre00g-8b/products/15797127643470",
      "CJ Source SKU": "CJYD206667601AZ",
      "CJ Product URL": "https://cjdropshipping.com/product/home-dining-table-coaster-western-style-placemat-p-2406230620351620400.html",
      "Variant Title": "Type B / 24 cm",
      "Variant SKU": "CM-CJYD206667601AZ-TYPE-B-24-CM",
      "Shopify Variant ID": "59517359292750",
      "Shopify Variant GID": "gid://shopify/ProductVariant/59517359292750",
      "Inventory Item ID": "57932563579214",
      "Inventory Item GID": "gid://shopify/InventoryItem/57932563579214",
      "Inventory Tracked": "FALSE",
      "Inventory Policy": "CONTINUE",
      "Option 1 Name": "Style",
      "Option 1 Value": "Type B",
      "Option 2 Name": "Size",
      "Option 2 Value": "24 cm",
      "Option 3 Name": "",
      "Option 3 Value": "",
      "CJ Connection Step": "CJ > Products > Store Products > Unconnected > Connect/Add Automatic Connection",
      "Connection Status": "needs-cj-connection"
    },
    {
      "Product Handle": "nora-round-cotton-trivet",
      "Product Title": "Nora Round Cotton Trivet",
      "Product Status": "ACTIVE",
      "Shopify Product ID": "15797127643470",
      "Shopify Product GID": "gid://shopify/Product/15797127643470",
      "Shopify Admin URL": "https://admin.shopify.com/store/vre00g-8b/products/15797127643470",
      "CJ Source SKU": "CJYD206667601AZ",
      "CJ Product URL": "https://cjdropshipping.com/product/home-dining-table-coaster-western-style-placemat-p-2406230620351620400.html",
      "Variant Title": "Type B / 30 cm",
      "Variant SKU": "CM-CJYD206667601AZ-TYPE-B-30-CM",
      "Shopify Variant ID": "59517359325518",
      "Shopify Variant GID": "gid://shopify/ProductVariant/59517359325518",
      "Inventory Item ID": "57932563611982",
      "Inventory Item GID": "gid://shopify/InventoryItem/57932563611982",
      "Inventory Tracked": "FALSE",
      "Inventory Policy": "CONTINUE",
      "Option 1 Name": "Style",
      "Option 1 Value": "Type B",
      "Option 2 Name": "Size",
      "Option 2 Value": "30 cm",
      "Option 3 Name": "",
      "Option 3 Value": "",
      "CJ Connection Step": "CJ > Products > Store Products > Unconnected > Connect/Add Automatic Connection",
      "Connection Status": "needs-cj-connection"
    },
    {
      "Product Handle": "nora-round-cotton-trivet",
      "Product Title": "Nora Round Cotton Trivet",
      "Product Status": "ACTIVE",
      "Shopify Product ID": "15797127643470",
      "Shopify Product GID": "gid://shopify/Product/15797127643470",
      "Shopify Admin URL": "https://admin.shopify.com/store/vre00g-8b/products/15797127643470",
      "CJ Source SKU": "CJYD206667601AZ",
      "CJ Product URL": "https://cjdropshipping.com/product/home-dining-table-coaster-western-style-placemat-p-2406230620351620400.html",
      "Variant Title": "Type C / 18 cm",
      "Variant SKU": "CM-CJYD206667601AZ-TYPE-C-18-CM",
      "Shopify Variant ID": "59517359358286",
      "Shopify Variant GID": "gid://shopify/ProductVariant/59517359358286",
      "Inventory Item ID": "57932563644750",
      "Inventory Item GID": "gid://shopify/InventoryItem/57932563644750",
      "Inventory Tracked": "FALSE",
      "Inventory Policy": "CONTINUE",
      "Option 1 Name": "Style",
      "Option 1 Value": "Type C",
      "Option 2 Name": "Size",
      "Option 2 Value": "18 cm",
      "Option 3 Name": "",
      "Option 3 Value": "",
      "CJ Connection Step": "CJ > Products > Store Products > Unconnected > Connect/Add Automatic Connection",
      "Connection Status": "needs-cj-connection"
    },
    {
      "Product Handle": "nora-round-cotton-trivet",
      "Product Title": "Nora Round Cotton Trivet",
      "Product Status": "ACTIVE",
      "Shopify Product ID": "15797127643470",
      "Shopify Product GID": "gid://shopify/Product/15797127643470",
      "Shopify Admin URL": "https://admin.shopify.com/store/vre00g-8b/products/15797127643470",
      "CJ Source SKU": "CJYD206667601AZ",
      "CJ Product URL": "https://cjdropshipping.com/product/home-dining-table-coaster-western-style-placemat-p-2406230620351620400.html",
      "Variant Title": "Type C / 24 cm",
      "Variant SKU": "CM-CJYD206667601AZ-TYPE-C-24-CM",
      "Shopify Variant ID": "59517359391054",
      "Shopify Variant GID": "gid://shopify/ProductVariant/59517359391054",
      "Inventory Item ID": "57932563677518",
      "Inventory Item GID": "gid://shopify/InventoryItem/57932563677518",
      "Inventory Tracked": "FALSE",
      "Inventory Policy": "CONTINUE",
      "Option 1 Name": "Style",
      "Option 1 Value": "Type C",
      "Option 2 Name": "Size",
      "Option 2 Value": "24 cm",
      "Option 3 Name": "",
      "Option 3 Value": "",
      "CJ Connection Step": "CJ > Products > Store Products > Unconnected > Connect/Add Automatic Connection",
      "Connection Status": "needs-cj-connection"
    },
    {
      "Product Handle": "nora-round-cotton-trivet",
      "Product Title": "Nora Round Cotton Trivet",
      "Product Status": "ACTIVE",
      "Shopify Product ID": "15797127643470",
      "Shopify Product GID": "gid://shopify/Product/15797127643470",
      "Shopify Admin URL": "https://admin.shopify.com/store/vre00g-8b/products/15797127643470",
      "CJ Source SKU": "CJYD206667601AZ",
      "CJ Product URL": "https://cjdropshipping.com/product/home-dining-table-coaster-western-style-placemat-p-2406230620351620400.html",
      "Variant Title": "Type C / 30 cm",
      "Variant SKU": "CM-CJYD206667601AZ-TYPE-C-30-CM",
      "Shopify Variant ID": "59517359423822",
      "Shopify Variant GID": "gid://shopify/ProductVariant/59517359423822",
      "Inventory Item ID": "57932563710286",
      "Inventory Item GID": "gid://shopify/InventoryItem/57932563710286",
      "Inventory Tracked": "FALSE",
      "Inventory Policy": "CONTINUE",
      "Option 1 Name": "Style",
      "Option 1 Value": "Type C",
      "Option 2 Name": "Size",
      "Option 2 Value": "30 cm",
      "Option 3 Name": "",
      "Option 3 Value": "",
      "CJ Connection Step": "CJ > Products > Store Products > Unconnected > Connect/Add Automatic Connection",
      "Connection Status": "needs-cj-connection"
    },
    {
      "Product Handle": "tali-tassel-table-mat",
      "Product Title": "Tali Tassel Table Mat",
      "Product Status": "ACTIVE",
      "Shopify Product ID": "15797127676238",
      "Shopify Product GID": "gid://shopify/Product/15797127676238",
      "Shopify Admin URL": "https://admin.shopify.com/store/vre00g-8b/products/15797127676238",
      "CJ Source SKU": "CJCJ177046101AZ",
      "CJ Product URL": "https://cjdropshipping.com/product/tassel-grass-insulated-dining-table-mat-p-1664950078802505728.html",
      "Variant Title": "Small",
      "Variant SKU": "CM-CJCJ177046101AZ-SMALL",
      "Shopify Variant ID": "59517359456590",
      "Shopify Variant GID": "gid://shopify/ProductVariant/59517359456590",
      "Inventory Item ID": "57932563743054",
      "Inventory Item GID": "gid://shopify/InventoryItem/57932563743054",
      "Inventory Tracked": "FALSE",
      "Inventory Policy": "CONTINUE",
      "Option 1 Name": "Size",
      "Option 1 Value": "Small",
      "Option 2 Name": "",
      "Option 2 Value": "",
      "Option 3 Name": "",
      "Option 3 Value": "",
      "CJ Connection Step": "CJ > Products > Store Products > Unconnected > Connect/Add Automatic Connection",
      "Connection Status": "needs-cj-connection"
    },
    {
      "Product Handle": "tali-tassel-table-mat",
      "Product Title": "Tali Tassel Table Mat",
      "Product Status": "ACTIVE",
      "Shopify Product ID": "15797127676238",
      "Shopify Product GID": "gid://shopify/Product/15797127676238",
      "Shopify Admin URL": "https://admin.shopify.com/store/vre00g-8b/products/15797127676238",
      "CJ Source SKU": "CJCJ177046101AZ",
      "CJ Product URL": "https://cjdropshipping.com/product/tassel-grass-insulated-dining-table-mat-p-1664950078802505728.html",
      "Variant Title": "Large",
      "Variant SKU": "CM-CJCJ177046101AZ-LARGE",
      "Shopify Variant ID": "59517359489358",
      "Shopify Variant GID": "gid://shopify/ProductVariant/59517359489358",
      "Inventory Item ID": "57932563775822",
      "Inventory Item GID": "gid://shopify/InventoryItem/57932563775822",
      "Inventory Tracked": "FALSE",
      "Inventory Policy": "CONTINUE",
      "Option 1 Name": "Size",
      "Option 1 Value": "Large",
      "Option 2 Name": "",
      "Option 2 Value": "",
      "Option 3 Name": "",
      "Option 3 Value": "",
      "CJ Connection Step": "CJ > Products > Store Products > Unconnected > Connect/Add Automatic Connection",
      "Connection Status": "needs-cj-connection"
    }
  ]
}
